satsim/__init__.py
satsim/cli.py
satsim/config.py
satsim/satsim.py
satsim/dataset/__init__.py
satsim/dataset/augment.py
satsim/generator/__init__.py
satsim/generator/obs/__init__.py
satsim/generator/obs/breakup.py
satsim/generator/obs/cso.py
satsim/generator/obs/geometry.py
satsim/generator/obs/io.py
satsim/generator/obs/rpo.py
satsim/geometry/__init__.py
satsim/geometry/analytic_obs.py
satsim/geometry/astrometric.py
satsim/geometry/csvsc.py
satsim/geometry/draw.py
satsim/geometry/ephemeris.py
satsim/geometry/greatcircle.py
satsim/geometry/observation.py
satsim/geometry/photometric.py
satsim/geometry/random.py
satsim/geometry/sgp4.py
satsim/geometry/shadow.py
satsim/geometry/sprite.py
satsim/geometry/sstr7.py
satsim/geometry/transform.py
satsim/geometry/twobody.py
satsim/geometry/wcs.py
satsim/image/__init__.py
satsim/image/augment.py
satsim/image/fpa.py
satsim/image/model.py
satsim/image/noise.py
satsim/image/psf.py
satsim/image/render.py
satsim/io/__init__.py
satsim/io/analytical.py
satsim/io/czml.py
satsim/io/fits.py
satsim/io/image.py
satsim/io/satnet.py
satsim/math/__init__.py
satsim/math/angle.py
satsim/math/const.py
satsim/math/conv.py
satsim/math/fft.py
satsim/math/interpolate.py
satsim/math/random.py
satsim/math/stats.py
satsim/pipeline/__init__.py
satsim/radar/__init__.py
satsim/radar/monostatic.py
satsim/radar/simulator.py
satsim/tfa/__init__.py
satsim/tfa/image/__init__.py
satsim/tfa/image/transform_ops.py
satsim/tfa/image/translate_ops.py
satsim/tfa/image/utils.py
satsim/tfa/utils/__init__.py
satsim/tfa/utils/test_utils.py
satsim/tfa/utils/types.py
satsim/time/__init__.py
satsim/util/__init__.py
satsim/util/python.py
satsim/util/system.py
satsim/util/thread.py
satsim/util/timer.py
satsim/vecmath/Cartesian2.py
satsim/vecmath/Cartesian3.py
satsim/vecmath/Cartesian4.py
satsim/vecmath/Matrix2.py
satsim/vecmath/Matrix3.py
satsim/vecmath/Matrix4.py
satsim/vecmath/Quaternion.py
satsim/vecmath/__init__.py
satsim-0.22.2.dist-info/AUTHORS.rst
satsim-0.22.2.dist-info/METADATA
satsim-0.22.2.dist-info/WHEEL
satsim-0.22.2.dist-info/entry_points.txt
satsim-0.22.2.dist-info/top_level.txt
satsim-0.22.2.dist-info/RECORD
