Metadata-Version: 2.1
Name: satsim
Version: 0.22.2
Summary: Satellite observation and scene simulator.
Home-page: https://github.com/ssc-ai/satsim
Author: Alex Cabello
Author-email: alexander.cabello@algoritics.com
License: UNKNOWN
Keywords: satsim
Platform: UNKNOWN
Classifier: Development Status :: 4 - Beta
Classifier: Intended Audience :: Developers
Classifier: Natural Language :: English
Classifier: Programming Language :: Python :: 3.8
Classifier: Programming Language :: Python :: 3.9
Classifier: Programming Language :: Python :: 3.10
Classifier: Programming Language :: Python :: 3.11
Classifier: Programming Language :: Python :: 3.12
License-File: AUTHORS.rst
Requires-Dist: Click (>=8.1)
Requires-Dist: Cython (>=0.29.0)
Requires-Dist: scikit-image (>=0.19.3)
Requires-Dist: Pillow (>=9.0)
Requires-Dist: numpy (>=1.21.0)
Requires-Dist: PyYAML (>=6.0)
Requires-Dist: matplotlib (>=3.7.0)
Requires-Dist: astropy (<6,>=5.2.1)
Requires-Dist: apng (>=0.3.4)
Requires-Dist: scipy (>=1.10)
Requires-Dist: tensorflow (>=2.4)
Requires-Dist: skyfield (>=1.45)
Requires-Dist: sgp4 (>=2.21)
Requires-Dist: poppy (>=1.0.3)
Requires-Dist: diskcache (>=5.0.3)
Requires-Dist: pydash (>=4.9.0)
Requires-Dist: asdf (<3,>=2.14.3)
Requires-Dist: pygc (>=1.3.0)
Requires-Dist: numba (>=0.56.0)
Requires-Dist: pooch (>=1.6.0)
Requires-Dist: czmlpy (>=0.9.0)
Requires-Dist: tifffile (>=2023.4.12)
Requires-Dist: imagecodecs (>=2023.3.16)
